pg_export/__init__.py
pg_export/acl.py
pg_export/extractor.py
pg_export/filters.py
pg_export/main.py
pg_export/renderer.py
pg_export/pg_items/__init__.py
pg_export/pg_items/aggregate.py
pg_export/pg_items/cast.py
pg_export/pg_items/domain.py
pg_export/pg_items/event_trigger.py
pg_export/pg_items/extension.py
pg_export/pg_items/function.py
pg_export/pg_items/item.py
pg_export/pg_items/language.py
pg_export/pg_items/operator.py
pg_export/pg_items/publication.py
pg_export/pg_items/schema.py
pg_export/pg_items/sequence.py
pg_export/pg_items/server.py
pg_export/pg_items/table.py
pg_export/pg_items/type.py
pg_export/pg_items/view.py
pg_export/templates/greenplum/in/_rule.sql
pg_export/templates/greenplum/in/_trigger.sql
pg_export/templates/greenplum/in/aggregate.sql
pg_export/templates/greenplum/in/function.sql
pg_export/templates/greenplum/in/publication.sql
pg_export/templates/greenplum/in/sequence.sql
pg_export/templates/greenplum/in/table.sql
pg_export/templates/greenplum/in/view.sql
pg_export/templates/greenplum/out/function.sql
pg_export/templates/greenplum/out/table.sql
pg_export/templates/postgresql/in/_argument.sql
pg_export/templates/postgresql/in/_attribute.sql
pg_export/templates/postgresql/in/_constraint.sql
pg_export/templates/postgresql/in/_index.sql
pg_export/templates/postgresql/in/_index_columns.sql
pg_export/templates/postgresql/in/_join_description_as_d.sql
pg_export/templates/postgresql/in/_namespace_filter.sql
pg_export/templates/postgresql/in/_not_part_of_extension.sql
pg_export/templates/postgresql/in/_rule.sql
pg_export/templates/postgresql/in/_trigger.sql
pg_export/templates/postgresql/in/aggregate.sql
pg_export/templates/postgresql/in/cast.sql
pg_export/templates/postgresql/in/directory.sql
pg_export/templates/postgresql/in/domain.sql
pg_export/templates/postgresql/in/event_trigger.sql
pg_export/templates/postgresql/in/extension.sql
pg_export/templates/postgresql/in/function.sql
pg_export/templates/postgresql/in/language.sql
pg_export-3.11.0.dist-info/licenses/LICENSE
pg_export-3.11.0.dist-info/METADATA
pg_export-3.11.0.dist-info/WHEEL
pg_export-3.11.0.dist-info/entry_points.txt
pg_export-3.11.0.dist-info/top_level.txt
pg_export-3.11.0.dist-info/RECORD
